chilexpress/connector.py
chilexpress/handler.py
chilexpress/settings.py
corona_chilexpress_logistica-1.0.12.dist-info/licenses/LICENSE
corona_chilexpress_logistica-1.0.12.dist-info/METADATA
corona_chilexpress_logistica-1.0.12.dist-info/WHEEL
corona_chilexpress_logistica-1.0.12.dist-info/top_level.txt
corona_chilexpress_logistica-1.0.12.dist-info/RECORD
